export/__init__.py
export/belns.py
export/famplex.belns
export/famplex.obo
export/famplex_groundings.tsv
export/hgnc_ids.py
export/hgnc_symbol_map.csv
export/obo.py
export/reach_bioresources.py
export/relations_graph.py
famplex/__init__.py
famplex/api.py
famplex/graph.py
famplex/load.py
famplex/locations.py
famplex/pages.py
famplex/html/__init__.py
famplex/html/__main__.py
famplex/html/api.py
famplex/import/__init__.py
famplex/import/descriptions.py
famplex/tests/__init__.py
famplex/tests/test_api.py
famplex/tests/test_load.py
famplex-0.0.5.data/data/lib/python3.10/site-packages/famplex/exports/famplex.belns
famplex-0.0.5.data/data/lib/python3.10/site-packages/famplex/exports/famplex.obo
famplex-0.0.5.data/data/lib/python3.10/site-packages/famplex/exports/famplex_groundings.tsv
famplex-0.0.5.data/data/lib/python3.10/site-packages/famplex/exports/hgnc_symbol_map.csv
famplex-0.0.5.data/data/lib/python3.10/site-packages/famplex/resources/descriptions.csv
famplex-0.0.5.data/data/lib/python3.10/site-packages/famplex/resources/entities.csv
famplex-0.0.5.data/data/lib/python3.10/site-packages/famplex/resources/equivalences.csv
famplex-0.0.5.data/data/lib/python3.10/site-packages/famplex/resources/gene_prefixes.csv
famplex-0.0.5.data/data/lib/python3.10/site-packages/famplex/resources/grounding_map.csv
famplex-0.0.5.data/data/lib/python3.10/site-packages/famplex/resources/relations.csv
famplex-0.0.5.dist-info/LICENSE.txt
famplex-0.0.5.dist-info/METADATA
famplex-0.0.5.dist-info/WHEEL
famplex-0.0.5.dist-info/top_level.txt
famplex-0.0.5.dist-info/RECORD
