Metadata-Version: 2.1
Name: famplex
Version: 0.0.5
Summary: Resources for grounding protein complexes and families from text and describing their hierarchical relationships.
Home-page: https://github.com/sorgerlab/famplex
Author: Famplex Developers, Harvard Medical School
Classifier: Development Status :: 4 - Beta
Classifier: Programming Language :: Python :: 3.5
Classifier: Programming Language :: Python :: 3.6
Classifier: Programming Language :: Python :: 3.7
Classifier: Programming Language :: Python :: 3.8
License-File: LICENSE.txt
Provides-Extra: html
Requires-Dist: requests ; extra == 'html'
Requires-Dist: tqdm ; extra == 'html'
Requires-Dist: pandas ; extra == 'html'
Requires-Dist: click ; extra == 'html'
Requires-Dist: jinja2 ; extra == 'html'
Requires-Dist: numpy (<2) ; extra == 'html'
Provides-Extra: test
Requires-Dist: pytest ; extra == 'test'
